{
  "arc_order_hash": "fcd2291f358d392f365241dec7a3c4968de31e7efdeda3b6ee525de2752d62cc",
  "arcs": [
    {
      "edge_idx": 0,
      "source": "0",
      "source_match_position": 0,
      "source_type": "Pair",
      "target": "1",
      "target_type": "Pair"
    },
    {
      "edge_idx": 1,
      "source": "0",
      "source_match_position": 1,
      "source_type": "Pair",
      "target": "16",
      "target_type": "Pair"
    },
    {
      "edge_idx": 2,
      "source": "0",
      "source_match_position": 2,
      "source_type": "Pair",
      "target": "17",
      "target_type": "Pair"
    },
    {
      "edge_idx": 3,
      "source": "0",
      "source_match_position": 3,
      "source_type": "Pair",
      "target": "19",
      "target_type": "Pair"
    },
    {
      "edge_idx": 4,
      "source": "2",
      "source_match_position": 0,
      "source_type": "Pair",
      "target": "1",
      "target_type": "Pair"
    },
    {
      "edge_idx": 5,
      "source": "2",
      "source_match_position": 1,
      "source_type": "Pair",
      "target": "6",
      "target_type": "Pair"
    },
    {
      "edge_idx": 6,
      "source": "2",
      "source_match_position": 2,
      "source_type": "Pair",
      "target": "14",
      "target_type": "Pair"
    },
    {
      "edge_idx": 7,
      "source": "2",
      "source_match_position": 3,
      "source_type": "Pair",
      "target": "16",
      "target_type": "Pair"
    },
    {
      "edge_idx": 8,
      "source": "4",
      "source_match_position": 0,
      "source_type": "Pair",
      "target": "2",
      "target_type": "Pair"
    },
    {
      "edge_idx": 9,
      "source": "4",
      "source_match_position": 1,
      "source_type": "Pair",
      "target": "16",
      "target_type": "Pair"
    },
    {
      "edge_idx": 10,
      "source": "5",
      "source_match_position": 0,
      "source_type": "Pair",
      "target": "0",
      "target_type": "Pair"
    },
    {
      "edge_idx": 11,
      "source": "5",
      "source_match_position": 1,
      "source_type": "Pair",
      "target": "1",
      "target_type": "Pair"
    },
    {
      "edge_idx": 12,
      "source": "5",
      "source_match_position": 2,
      "source_type": "Pair",
      "target": "2",
      "target_type": "Pair"
    },
    {
      "edge_idx": 13,
      "source": "5",
      "source_match_position": 3,
      "source_type": "Pair",
      "target": "10",
      "target_type": "Pair"
    },
    {
      "edge_idx": 14,
      "source": "5",
      "source_match_position": 4,
      "source_type": "Pair",
      "target": "11",
      "target_type": "Pair"
    },
    {
      "edge_idx": 15,
      "source": "5",
      "source_match_position": 5,
      "source_type": "Pair",
      "target": "18",
      "target_type": "Pair"
    },
    {
      "edge_idx": 16,
      "source": "5",
      "source_match_position": 6,
      "source_type": "Pair",
      "target": "19",
      "target_type": "Pair"
    },
    {
      "edge_idx": 17,
      "source": "6",
      "source_match_position": 0,
      "source_type": "Pair",
      "target": "0",
      "target_type": "Pair"
    },
    {
      "edge_idx": 18,
      "source": "6",
      "source_match_position": 1,
      "source_type": "Pair",
      "target": "8",
      "target_type": "Pair"
    },
    {
      "edge_idx": 19,
      "source": "6",
      "source_match_position": 2,
      "source_type": "Pair",
      "target": "11",
      "target_type": "Pair"
    },
    {
      "edge_idx": 20,
      "source": "6",
      "source_match_position": 3,
      "source_type": "Pair",
      "target": "14",
      "target_type": "Pair"
    },
    {
      "edge_idx": 21,
      "source": "6",
      "source_match_position": 4,
      "source_type": "Pair",
      "target": "16",
      "target_type": "Pair"
    },
    {
      "edge_idx": 22,
      "source": "6",
      "source_match_position": 5,
      "source_type": "Pair",
      "target": "19",
      "target_type": "Pair"
    },
    {
      "edge_idx": 23,
      "source": "8",
      "source_match_position": 0,
      "source_type": "Pair",
      "target": "12",
      "target_type": "Pair"
    },
    {
      "edge_idx": 24,
      "source": "8",
      "source_match_position": 1,
      "source_type": "Pair",
      "target": "17",
      "target_type": "Pair"
    },
    {
      "edge_idx": 25,
      "source": "10",
      "source_match_position": 0,
      "source_type": "Pair",
      "target": "0",
      "target_type": "Pair"
    },
    {
      "edge_idx": 26,
      "source": "10",
      "source_match_position": 1,
      "source_type": "Pair",
      "target": "3",
      "target_type": "Pair"
    },
    {
      "edge_idx": 27,
      "source": "11",
      "source_match_position": 0,
      "source_type": "Pair",
      "target": "0",
      "target_type": "Pair"
    },
    {
      "edge_idx": 28,
      "source": "11",
      "source_match_position": 1,
      "source_type": "Pair",
      "target": "2",
      "target_type": "Pair"
    },
    {
      "edge_idx": 29,
      "source": "11",
      "source_match_position": 2,
      "source_type": "Pair",
      "target": "17",
      "target_type": "Pair"
    },
    {
      "edge_idx": 30,
      "source": "12",
      "source_match_position": 0,
      "source_type": "Pair",
      "target": "2",
      "target_type": "Pair"
    },
    {
      "edge_idx": 31,
      "source": "12",
      "source_match_position": 1,
      "source_type": "Pair",
      "target": "16",
      "target_type": "Pair"
    },
    {
      "edge_idx": 32,
      "source": "12",
      "source_match_position": 2,
      "source_type": "Pair",
      "target": "17",
      "target_type": "Pair"
    },
    {
      "edge_idx": 33,
      "source": "13",
      "source_match_position": 0,
      "source_type": "Pair",
      "target": "17",
      "target_type": "Pair"
    },
    {
      "edge_idx": 34,
      "source": "13",
      "source_match_position": 1,
      "source_type": "Pair",
      "target": "18",
      "target_type": "Pair"
    },
    {
      "edge_idx": 35,
      "source": "14",
      "source_match_position": 0,
      "source_type": "Pair",
      "target": "1",
      "target_type": "Pair"
    },
    {
      "edge_idx": 36,
      "source": "14",
      "source_match_position": 1,
      "source_type": "Pair",
      "target": "16",
      "target_type": "Pair"
    },
    {
      "edge_idx": 37,
      "source": "14",
      "source_match_position": 2,
      "source_type": "Pair",
      "target": "17",
      "target_type": "Pair"
    },
    {
      "edge_idx": 38,
      "source": "14",
      "source_match_position": 3,
      "source_type": "Pair",
      "target": "18",
      "target_type": "Pair"
    },
    {
      "edge_idx": 39,
      "source": "19",
      "source_match_position": 0,
      "source_type": "Pair",
      "target": "16",
      "target_type": "Pair"
    },
    {
      "edge_idx": 40,
      "source": "20",
      "source_match_position": 0,
      "source_type": "Pair",
      "target": "8",
      "target_type": "Pair"
    },
    {
      "edge_idx": 41,
      "source": "20",
      "source_match_position": 1,
      "source_type": "Pair",
      "target": "14",
      "target_type": "Pair"
    },
    {
      "edge_idx": 42,
      "source": "20",
      "source_match_position": 2,
      "source_type": "Pair",
      "target": "16",
      "target_type": "Pair"
    },
    {
      "edge_idx": 43,
      "source": "20",
      "source_match_position": 3,
      "source_type": "Pair",
      "target": "18",
      "target_type": "Pair"
    },
    {
      "edge_idx": 44,
      "source": "20",
      "source_match_position": 4,
      "source_type": "Pair",
      "target": "19",
      "target_type": "Pair"
    },
    {
      "edge_idx": 45,
      "source": "21",
      "source_match_position": 0,
      "source_type": "NDD",
      "target": "0",
      "target_type": "Pair"
    },
    {
      "edge_idx": 46,
      "source": "21",
      "source_match_position": 1,
      "source_type": "NDD",
      "target": "1",
      "target_type": "Pair"
    },
    {
      "edge_idx": 47,
      "source": "21",
      "source_match_position": 2,
      "source_type": "NDD",
      "target": "6",
      "target_type": "Pair"
    },
    {
      "edge_idx": 48,
      "source": "21",
      "source_match_position": 3,
      "source_type": "NDD",
      "target": "8",
      "target_type": "Pair"
    },
    {
      "edge_idx": 49,
      "source": "21",
      "source_match_position": 4,
      "source_type": "NDD",
      "target": "11",
      "target_type": "Pair"
    },
    {
      "edge_idx": 50,
      "source": "21",
      "source_match_position": 5,
      "source_type": "NDD",
      "target": "16",
      "target_type": "Pair"
    },
    {
      "edge_idx": 51,
      "source": "21",
      "source_match_position": 6,
      "source_type": "NDD",
      "target": "17",
      "target_type": "Pair"
    },
    {
      "edge_idx": 52,
      "source": "21",
      "source_match_position": 7,
      "source_type": "NDD",
      "target": "19",
      "target_type": "Pair"
    },
    {
      "edge_idx": 53,
      "source": "22",
      "source_match_position": 0,
      "source_type": "NDD",
      "target": "0",
      "target_type": "Pair"
    },
    {
      "edge_idx": 54,
      "source": "22",
      "source_match_position": 1,
      "source_type": "NDD",
      "target": "1",
      "target_type": "Pair"
    },
    {
      "edge_idx": 55,
      "source": "22",
      "source_match_position": 2,
      "source_type": "NDD",
      "target": "2",
      "target_type": "Pair"
    },
    {
      "edge_idx": 56,
      "source": "22",
      "source_match_position": 3,
      "source_type": "NDD",
      "target": "10",
      "target_type": "Pair"
    },
    {
      "edge_idx": 57,
      "source": "22",
      "source_match_position": 4,
      "source_type": "NDD",
      "target": "17",
      "target_type": "Pair"
    }
  ],
  "feasible_candidates": [
    {
      "edges": [
        5,
        19,
        28
      ],
      "length": 3,
      "nodes": [
        "2",
        "6",
        "11"
      ],
      "signature": "cycle:2->6->11->2",
      "type": "cycle"
    },
    {
      "edges": [
        45
      ],
      "length": 1,
      "nodes": [
        "21",
        "0"
      ],
      "signature": "chain:21->0",
      "type": "chain"
    },
    {
      "edges": [
        45,
        0
      ],
      "length": 2,
      "nodes": [
        "21",
        "0",
        "1"
      ],
      "signature": "chain:21->0->1",
      "type": "chain"
    },
    {
      "edges": [
        45,
        1
      ],
      "length": 2,
      "nodes": [
        "21",
        "0",
        "16"
      ],
      "signature": "chain:21->0->16",
      "type": "chain"
    },
    {
      "edges": [
        45,
        2
      ],
      "length": 2,
      "nodes": [
        "21",
        "0",
        "17"
      ],
      "signature": "chain:21->0->17",
      "type": "chain"
    },
    {
      "edges": [
        45,
        3
      ],
      "length": 2,
      "nodes": [
        "21",
        "0",
        "19"
      ],
      "signature": "chain:21->0->19",
      "type": "chain"
    },
    {
      "edges": [
        45,
        3,
        39
      ],
      "length": 3,
      "nodes": [
        "21",
        "0",
        "19",
        "16"
      ],
      "signature": "chain:21->0->19->16",
      "type": "chain"
    },
    {
      "edges": [
        46
      ],
      "length": 1,
      "nodes": [
        "21",
        "1"
      ],
      "signature": "chain:21->1",
      "type": "chain"
    },
    {
      "edges": [
        49
      ],
      "length": 1,
      "nodes": [
        "21",
        "11"
      ],
      "signature": "chain:21->11",
      "type": "chain"
    },
    {
      "edges": [
        49,
        27
      ],
      "length": 2,
      "nodes": [
        "21",
        "11",
        "0"
      ],
      "signature": "chain:21->11->0",
      "type": "chain"
    },
    {
      "edges": [
        49,
        27,
        0
      ],
      "length": 3,
      "nodes": [
        "21",
        "11",
        "0",
        "1"
      ],
      "signature": "chain:21->11->0->1",
      "type": "chain"
    },
    {
      "edges": [
        49,
        27,
        1
      ],
      "length": 3,
      "nodes": [
        "21",
        "11",
        "0",
        "16"
      ],
      "signature": "chain:21->11->0->16",
      "type": "chain"
    },
    {
      "edges": [
        49,
        27,
        2
      ],
      "length": 3,
      "nodes": [
        "21",
        "11",
        "0",
        "17"
      ],
      "signature": "chain:21->11->0->17",
      "type": "chain"
    },
    {
      "edges": [
        49,
        27,
        3
      ],
      "length": 3,
      "nodes": [
        "21",
        "11",
        "0",
        "19"
      ],
      "signature": "chain:21->11->0->19",
      "type": "chain"
    },
    {
      "edges": [
        49,
        27,
        3,
        39
      ],
      "length": 4,
      "nodes": [
        "21",
        "11",
        "0",
        "19",
        "16"
      ],
      "signature": "chain:21->11->0->19->16",
      "type": "chain"
    },
    {
      "edges": [
        49,
        29
      ],
      "length": 2,
      "nodes": [
        "21",
        "11",
        "17"
      ],
      "signature": "chain:21->11->17",
      "type": "chain"
    },
    {
      "edges": [
        49,
        28
      ],
      "length": 2,
      "nodes": [
        "21",
        "11",
        "2"
      ],
      "signature": "chain:21->11->2",
      "type": "chain"
    },
    {
      "edges": [
        49,
        28,
        4
      ],
      "length": 3,
      "nodes": [
        "21",
        "11",
        "2",
        "1"
      ],
      "signature": "chain:21->11->2->1",
      "type": "chain"
    },
    {
      "edges": [
        49,
        28,
        6
      ],
      "length": 3,
      "nodes": [
        "21",
        "11",
        "2",
        "14"
      ],
      "signature": "chain:21->11->2->14",
      "type": "chain"
    },
    {
      "edges": [
        49,
        28,
        6,
        35
      ],
      "length": 4,
      "nodes": [
        "21",
        "11",
        "2",
        "14",
        "1"
      ],
      "signature": "chain:21->11->2->14->1",
      "type": "chain"
    },
    {
      "edges": [
        49,
        28,
        6,
        36
      ],
      "length": 4,
      "nodes": [
        "21",
        "11",
        "2",
        "14",
        "16"
      ],
      "signature": "chain:21->11->2->14->16",
      "type": "chain"
    },
    {
      "edges": [
        49,
        28,
        6,
        37
      ],
      "length": 4,
      "nodes": [
        "21",
        "11",
        "2",
        "14",
        "17"
      ],
      "signature": "chain:21->11->2->14->17",
      "type": "chain"
    },
    {
      "edges": [
        49,
        28,
        6,
        38
      ],
      "length": 4,
      "nodes": [
        "21",
        "11",
        "2",
        "14",
        "18"
      ],
      "signature": "chain:21->11->2->14->18",
      "type": "chain"
    },
    {
      "edges": [
        49,
        28,
        7
      ],
      "length": 3,
      "nodes": [
        "21",
        "11",
        "2",
        "16"
      ],
      "signature": "chain:21->11->2->16",
      "type": "chain"
    },
    {
      "edges": [
        49,
        28,
        5
      ],
      "length": 3,
      "nodes": [
        "21",
        "11",
        "2",
        "6"
      ],
      "signature": "chain:21->11->2->6",
      "type": "chain"
    },
    {
      "edges": [
        49,
        28,
        5,
        17
      ],
      "length": 4,
      "nodes": [
        "21",
        "11",
        "2",
        "6",
        "0"
      ],
      "signature": "chain:21->11->2->6->0",
      "type": "chain"
    },
    {
      "edges": [
        49,
        28,
        5,
        20
      ],
      "length": 4,
      "nodes": [
        "21",
        "11",
        "2",
        "6",
        "14"
      ],
      "signature": "chain:21->11->2->6->14",
      "type": "chain"
    },
    {
      "edges": [
        49,
        28,
        5,
        21
      ],
      "length": 4,
      "nodes": [
        "21",
        "11",
        "2",
        "6",
        "16"
      ],
      "signature": "chain:21->11->2->6->16",
      "type": "chain"
    },
    {
      "edges": [
        49,
        28,
        5,
        22
      ],
      "length": 4,
      "nodes": [
        "21",
        "11",
        "2",
        "6",
        "19"
      ],
      "signature": "chain:21->11->2->6->19",
      "type": "chain"
    },
    {
      "edges": [
        49,
        28,
        5,
        18
      ],
      "length": 4,
      "nodes": [
        "21",
        "11",
        "2",
        "6",
        "8"
      ],
      "signature": "chain:21->11->2->6->8",
      "type": "chain"
    },
    {
      "edges": [
        50
      ],
      "length": 1,
      "nodes": [
        "21",
        "16"
      ],
      "signature": "chain:21->16",
      "type": "chain"
    },
    {
      "edges": [
        51
      ],
      "length": 1,
      "nodes": [
        "21",
        "17"
      ],
      "signature": "chain:21->17",
      "type": "chain"
    },
    {
      "edges": [
        52
      ],
      "length": 1,
      "nodes": [
        "21",
        "19"
      ],
      "signature": "chain:21->19",
      "type": "chain"
    },
    {
      "edges": [
        52,
        39
      ],
      "length": 2,
      "nodes": [
        "21",
        "19",
        "16"
      ],
      "signature": "chain:21->19->16",
      "type": "chain"
    },
    {
      "edges": [
        47
      ],
      "length": 1,
      "nodes": [
        "21",
        "6"
      ],
      "signature": "chain:21->6",
      "type": "chain"
    },
    {
      "edges": [
        47,
        17
      ],
      "length": 2,
      "nodes": [
        "21",
        "6",
        "0"
      ],
      "signature": "chain:21->6->0",
      "type": "chain"
    },
    {
      "edges": [
        47,
        17,
        0
      ],
      "length": 3,
      "nodes": [
        "21",
        "6",
        "0",
        "1"
      ],
      "signature": "chain:21->6->0->1",
      "type": "chain"
    },
    {
      "edges": [
        47,
        17,
        1
      ],
      "length": 3,
      "nodes": [
        "21",
        "6",
        "0",
        "16"
      ],
      "signature": "chain:21->6->0->16",
      "type": "chain"
    },
    {
      "edges": [
        47,
        17,
        2
      ],
      "length": 3,
      "nodes": [
        "21",
        "6",
        "0",
        "17"
      ],
      "signature": "chain:21->6->0->17",
      "type": "chain"
    },
    {
      "edges": [
        47,
        17,
        3
      ],
      "length": 3,
      "nodes": [
        "21",
        "6",
        "0",
        "19"
      ],
      "signature": "chain:21->6->0->19",
      "type": "chain"
    },
    {
      "edges": [
        47,
        17,
        3,
        39
      ],
      "length": 4,
      "nodes": [
        "21",
        "6",
        "0",
        "19",
        "16"
      ],
      "signature": "chain:21->6->0->19->16",
      "type": "chain"
    },
    {
      "edges": [
        47,
        19
      ],
      "length": 2,
      "nodes": [
        "21",
        "6",
        "11"
      ],
      "signature": "chain:21->6->11",
      "type": "chain"
    },
    {
      "edges": [
        47,
        19,
        27
      ],
      "length": 3,
      "nodes": [
        "21",
        "6",
        "11",
        "0"
      ],
      "signature": "chain:21->6->11->0",
      "type": "chain"
    },
    {
      "edges": [
        47,
        19,
        27,
        0
      ],
      "length": 4,
      "nodes": [
        "21",
        "6",
        "11",
        "0",
        "1"
      ],
      "signature": "chain:21->6->11->0->1",
      "type": "chain"
    },
    {
      "edges": [
        47,
        19,
        27,
        1
      ],
      "length": 4,
      "nodes": [
        "21",
        "6",
        "11",
        "0",
        "16"
      ],
      "signature": "chain:21->6->11->0->16",
      "type": "chain"
    },
    {
      "edges": [
        47,
        19,
        27,
        2
      ],
      "length": 4,
      "nodes": [
        "21",
        "6",
        "11",
        "0",
        "17"
      ],
      "signature": "chain:21->6->11->0->17",
      "type": "chain"
    },
    {
      "edges": [
        47,
        19,
        27,
        3
      ],
      "length": 4,
      "nodes": [
        "21",
        "6",
        "11",
        "0",
        "19"
      ],
      "signature": "chain:21->6->11->0->19",
      "type": "chain"
    },
    {
      "edges": [
        47,
        19,
        29
      ],
      "length": 3,
      "nodes": [
        "21",
        "6",
        "11",
        "17"
      ],
      "signature": "chain:21->6->11->17",
      "type": "chain"
    },
    {
      "edges": [
        47,
        19,
        28
      ],
      "length": 3,
      "nodes": [
        "21",
        "6",
        "11",
        "2"
      ],
      "signature": "chain:21->6->11->2",
      "type": "chain"
    },
    {
      "edges": [
        47,
        19,
        28,
        4
      ],
      "length": 4,
      "nodes": [
        "21",
        "6",
        "11",
        "2",
        "1"
      ],
      "signature": "chain:21->6->11->2->1",
      "type": "chain"
    },
    {
      "edges": [
        47,
        19,
        28,
        6
      ],
      "length": 4,
      "nodes": [
        "21",
        "6",
        "11",
        "2",
        "14"
      ],
      "signature": "chain:21->6->11->2->14",
      "type": "chain"
    },
    {
      "edges": [
        47,
        19,
        28,
        7
      ],
      "length": 4,
      "nodes": [
        "21",
        "6",
        "11",
        "2",
        "16"
      ],
      "signature": "chain:21->6->11->2->16",
      "type": "chain"
    },
    {
      "edges": [
        47,
        20
      ],
      "length": 2,
      "nodes": [
        "21",
        "6",
        "14"
      ],
      "signature": "chain:21->6->14",
      "type": "chain"
    },
    {
      "edges": [
        47,
        20,
        35
      ],
      "length": 3,
      "nodes": [
        "21",
        "6",
        "14",
        "1"
      ],
      "signature": "chain:21->6->14->1",
      "type": "chain"
    },
    {
      "edges": [
        47,
        20,
        36
      ],
      "length": 3,
      "nodes": [
        "21",
        "6",
        "14",
        "16"
      ],
      "signature": "chain:21->6->14->16",
      "type": "chain"
    },
    {
      "edges": [
        47,
        20,
        37
      ],
      "length": 3,
      "nodes": [
        "21",
        "6",
        "14",
        "17"
      ],
      "signature": "chain:21->6->14->17",
      "type": "chain"
    },
    {
      "edges": [
        47,
        20,
        38
      ],
      "length": 3,
      "nodes": [
        "21",
        "6",
        "14",
        "18"
      ],
      "signature": "chain:21->6->14->18",
      "type": "chain"
    },
    {
      "edges": [
        47,
        21
      ],
      "length": 2,
      "nodes": [
        "21",
        "6",
        "16"
      ],
      "signature": "chain:21->6->16",
      "type": "chain"
    },
    {
      "edges": [
        47,
        22
      ],
      "length": 2,
      "nodes": [
        "21",
        "6",
        "19"
      ],
      "signature": "chain:21->6->19",
      "type": "chain"
    },
    {
      "edges": [
        47,
        22,
        39
      ],
      "length": 3,
      "nodes": [
        "21",
        "6",
        "19",
        "16"
      ],
      "signature": "chain:21->6->19->16",
      "type": "chain"
    },
    {
      "edges": [
        47,
        18
      ],
      "length": 2,
      "nodes": [
        "21",
        "6",
        "8"
      ],
      "signature": "chain:21->6->8",
      "type": "chain"
    },
    {
      "edges": [
        47,
        18,
        23
      ],
      "length": 3,
      "nodes": [
        "21",
        "6",
        "8",
        "12"
      ],
      "signature": "chain:21->6->8->12",
      "type": "chain"
    },
    {
      "edges": [
        47,
        18,
        23,
        31
      ],
      "length": 4,
      "nodes": [
        "21",
        "6",
        "8",
        "12",
        "16"
      ],
      "signature": "chain:21->6->8->12->16",
      "type": "chain"
    },
    {
      "edges": [
        47,
        18,
        23,
        32
      ],
      "length": 4,
      "nodes": [
        "21",
        "6",
        "8",
        "12",
        "17"
      ],
      "signature": "chain:21->6->8->12->17",
      "type": "chain"
    },
    {
      "edges": [
        47,
        18,
        23,
        30
      ],
      "length": 4,
      "nodes": [
        "21",
        "6",
        "8",
        "12",
        "2"
      ],
      "signature": "chain:21->6->8->12->2",
      "type": "chain"
    },
    {
      "edges": [
        47,
        18,
        24
      ],
      "length": 3,
      "nodes": [
        "21",
        "6",
        "8",
        "17"
      ],
      "signature": "chain:21->6->8->17",
      "type": "chain"
    },
    {
      "edges": [
        48
      ],
      "length": 1,
      "nodes": [
        "21",
        "8"
      ],
      "signature": "chain:21->8",
      "type": "chain"
    },
    {
      "edges": [
        48,
        23
      ],
      "length": 2,
      "nodes": [
        "21",
        "8",
        "12"
      ],
      "signature": "chain:21->8->12",
      "type": "chain"
    },
    {
      "edges": [
        48,
        23,
        31
      ],
      "length": 3,
      "nodes": [
        "21",
        "8",
        "12",
        "16"
      ],
      "signature": "chain:21->8->12->16",
      "type": "chain"
    },
    {
      "edges": [
        48,
        23,
        32
      ],
      "length": 3,
      "nodes": [
        "21",
        "8",
        "12",
        "17"
      ],
      "signature": "chain:21->8->12->17",
      "type": "chain"
    },
    {
      "edges": [
        48,
        23,
        30
      ],
      "length": 3,
      "nodes": [
        "21",
        "8",
        "12",
        "2"
      ],
      "signature": "chain:21->8->12->2",
      "type": "chain"
    },
    {
      "edges": [
        48,
        23,
        30,
        4
      ],
      "length": 4,
      "nodes": [
        "21",
        "8",
        "12",
        "2",
        "1"
      ],
      "signature": "chain:21->8->12->2->1",
      "type": "chain"
    },
    {
      "edges": [
        48,
        23,
        30,
        6
      ],
      "length": 4,
      "nodes": [
        "21",
        "8",
        "12",
        "2",
        "14"
      ],
      "signature": "chain:21->8->12->2->14",
      "type": "chain"
    },
    {
      "edges": [
        48,
        23,
        30,
        7
      ],
      "length": 4,
      "nodes": [
        "21",
        "8",
        "12",
        "2",
        "16"
      ],
      "signature": "chain:21->8->12->2->16",
      "type": "chain"
    },
    {
      "edges": [
        48,
        23,
        30,
        5
      ],
      "length": 4,
      "nodes": [
        "21",
        "8",
        "12",
        "2",
        "6"
      ],
      "signature": "chain:21->8->12->2->6",
      "type": "chain"
    },
    {
      "edges": [
        48,
        24
      ],
      "length": 2,
      "nodes": [
        "21",
        "8",
        "17"
      ],
      "signature": "chain:21->8->17",
      "type": "chain"
    },
    {
      "edges": [
        53
      ],
      "length": 1,
      "nodes": [
        "22",
        "0"
      ],
      "signature": "chain:22->0",
      "type": "chain"
    },
    {
      "edges": [
        53,
        0
      ],
      "length": 2,
      "nodes": [
        "22",
        "0",
        "1"
      ],
      "signature": "chain:22->0->1",
      "type": "chain"
    },
    {
      "edges": [
        53,
        1
      ],
      "length": 2,
      "nodes": [
        "22",
        "0",
        "16"
      ],
      "signature": "chain:22->0->16",
      "type": "chain"
    },
    {
      "edges": [
        53,
        2
      ],
      "length": 2,
      "nodes": [
        "22",
        "0",
        "17"
      ],
      "signature": "chain:22->0->17",
      "type": "chain"
    },
    {
      "edges": [
        53,
        3
      ],
      "length": 2,
      "nodes": [
        "22",
        "0",
        "19"
      ],
      "signature": "chain:22->0->19",
      "type": "chain"
    },
    {
      "edges": [
        53,
        3,
        39
      ],
      "length": 3,
      "nodes": [
        "22",
        "0",
        "19",
        "16"
      ],
      "signature": "chain:22->0->19->16",
      "type": "chain"
    },
    {
      "edges": [
        54
      ],
      "length": 1,
      "nodes": [
        "22",
        "1"
      ],
      "signature": "chain:22->1",
      "type": "chain"
    },
    {
      "edges": [
        56
      ],
      "length": 1,
      "nodes": [
        "22",
        "10"
      ],
      "signature": "chain:22->10",
      "type": "chain"
    },
    {
      "edges": [
        56,
        25
      ],
      "length": 2,
      "nodes": [
        "22",
        "10",
        "0"
      ],
      "signature": "chain:22->10->0",
      "type": "chain"
    },
    {
      "edges": [
        56,
        25,
        0
      ],
      "length": 3,
      "nodes": [
        "22",
        "10",
        "0",
        "1"
      ],
      "signature": "chain:22->10->0->1",
      "type": "chain"
    },
    {
      "edges": [
        56,
        25,
        1
      ],
      "length": 3,
      "nodes": [
        "22",
        "10",
        "0",
        "16"
      ],
      "signature": "chain:22->10->0->16",
      "type": "chain"
    },
    {
      "edges": [
        56,
        25,
        2
      ],
      "length": 3,
      "nodes": [
        "22",
        "10",
        "0",
        "17"
      ],
      "signature": "chain:22->10->0->17",
      "type": "chain"
    },
    {
      "edges": [
        56,
        25,
        3
      ],
      "length": 3,
      "nodes": [
        "22",
        "10",
        "0",
        "19"
      ],
      "signature": "chain:22->10->0->19",
      "type": "chain"
    },
    {
      "edges": [
        56,
        25,
        3,
        39
      ],
      "length": 4,
      "nodes": [
        "22",
        "10",
        "0",
        "19",
        "16"
      ],
      "signature": "chain:22->10->0->19->16",
      "type": "chain"
    },
    {
      "edges": [
        56,
        26
      ],
      "length": 2,
      "nodes": [
        "22",
        "10",
        "3"
      ],
      "signature": "chain:22->10->3",
      "type": "chain"
    },
    {
      "edges": [
        57
      ],
      "length": 1,
      "nodes": [
        "22",
        "17"
      ],
      "signature": "chain:22->17",
      "type": "chain"
    },
    {
      "edges": [
        55
      ],
      "length": 1,
      "nodes": [
        "22",
        "2"
      ],
      "signature": "chain:22->2",
      "type": "chain"
    },
    {
      "edges": [
        55,
        4
      ],
      "length": 2,
      "nodes": [
        "22",
        "2",
        "1"
      ],
      "signature": "chain:22->2->1",
      "type": "chain"
    },
    {
      "edges": [
        55,
        6
      ],
      "length": 2,
      "nodes": [
        "22",
        "2",
        "14"
      ],
      "signature": "chain:22->2->14",
      "type": "chain"
    },
    {
      "edges": [
        55,
        6,
        35
      ],
      "length": 3,
      "nodes": [
        "22",
        "2",
        "14",
        "1"
      ],
      "signature": "chain:22->2->14->1",
      "type": "chain"
    },
    {
      "edges": [
        55,
        6,
        36
      ],
      "length": 3,
      "nodes": [
        "22",
        "2",
        "14",
        "16"
      ],
      "signature": "chain:22->2->14->16",
      "type": "chain"
    },
    {
      "edges": [
        55,
        6,
        37
      ],
      "length": 3,
      "nodes": [
        "22",
        "2",
        "14",
        "17"
      ],
      "signature": "chain:22->2->14->17",
      "type": "chain"
    },
    {
      "edges": [
        55,
        6,
        38
      ],
      "length": 3,
      "nodes": [
        "22",
        "2",
        "14",
        "18"
      ],
      "signature": "chain:22->2->14->18",
      "type": "chain"
    },
    {
      "edges": [
        55,
        7
      ],
      "length": 2,
      "nodes": [
        "22",
        "2",
        "16"
      ],
      "signature": "chain:22->2->16",
      "type": "chain"
    },
    {
      "edges": [
        55,
        5
      ],
      "length": 2,
      "nodes": [
        "22",
        "2",
        "6"
      ],
      "signature": "chain:22->2->6",
      "type": "chain"
    },
    {
      "edges": [
        55,
        5,
        17
      ],
      "length": 3,
      "nodes": [
        "22",
        "2",
        "6",
        "0"
      ],
      "signature": "chain:22->2->6->0",
      "type": "chain"
    },
    {
      "edges": [
        55,
        5,
        17,
        0
      ],
      "length": 4,
      "nodes": [
        "22",
        "2",
        "6",
        "0",
        "1"
      ],
      "signature": "chain:22->2->6->0->1",
      "type": "chain"
    },
    {
      "edges": [
        55,
        5,
        17,
        1
      ],
      "length": 4,
      "nodes": [
        "22",
        "2",
        "6",
        "0",
        "16"
      ],
      "signature": "chain:22->2->6->0->16",
      "type": "chain"
    },
    {
      "edges": [
        55,
        5,
        17,
        2
      ],
      "length": 4,
      "nodes": [
        "22",
        "2",
        "6",
        "0",
        "17"
      ],
      "signature": "chain:22->2->6->0->17",
      "type": "chain"
    },
    {
      "edges": [
        55,
        5,
        17,
        3
      ],
      "length": 4,
      "nodes": [
        "22",
        "2",
        "6",
        "0",
        "19"
      ],
      "signature": "chain:22->2->6->0->19",
      "type": "chain"
    },
    {
      "edges": [
        55,
        5,
        19
      ],
      "length": 3,
      "nodes": [
        "22",
        "2",
        "6",
        "11"
      ],
      "signature": "chain:22->2->6->11",
      "type": "chain"
    },
    {
      "edges": [
        55,
        5,
        19,
        27
      ],
      "length": 4,
      "nodes": [
        "22",
        "2",
        "6",
        "11",
        "0"
      ],
      "signature": "chain:22->2->6->11->0",
      "type": "chain"
    },
    {
      "edges": [
        55,
        5,
        19,
        29
      ],
      "length": 4,
      "nodes": [
        "22",
        "2",
        "6",
        "11",
        "17"
      ],
      "signature": "chain:22->2->6->11->17",
      "type": "chain"
    },
    {
      "edges": [
        55,
        5,
        20
      ],
      "length": 3,
      "nodes": [
        "22",
        "2",
        "6",
        "14"
      ],
      "signature": "chain:22->2->6->14",
      "type": "chain"
    },
    {
      "edges": [
        55,
        5,
        20,
        35
      ],
      "length": 4,
      "nodes": [
        "22",
        "2",
        "6",
        "14",
        "1"
      ],
      "signature": "chain:22->2->6->14->1",
      "type": "chain"
    },
    {
      "edges": [
        55,
        5,
        20,
        36
      ],
      "length": 4,
      "nodes": [
        "22",
        "2",
        "6",
        "14",
        "16"
      ],
      "signature": "chain:22->2->6->14->16",
      "type": "chain"
    },
    {
      "edges": [
        55,
        5,
        20,
        37
      ],
      "length": 4,
      "nodes": [
        "22",
        "2",
        "6",
        "14",
        "17"
      ],
      "signature": "chain:22->2->6->14->17",
      "type": "chain"
    },
    {
      "edges": [
        55,
        5,
        20,
        38
      ],
      "length": 4,
      "nodes": [
        "22",
        "2",
        "6",
        "14",
        "18"
      ],
      "signature": "chain:22->2->6->14->18",
      "type": "chain"
    },
    {
      "edges": [
        55,
        5,
        21
      ],
      "length": 3,
      "nodes": [
        "22",
        "2",
        "6",
        "16"
      ],
      "signature": "chain:22->2->6->16",
      "type": "chain"
    },
    {
      "edges": [
        55,
        5,
        22
      ],
      "length": 3,
      "nodes": [
        "22",
        "2",
        "6",
        "19"
      ],
      "signature": "chain:22->2->6->19",
      "type": "chain"
    },
    {
      "edges": [
        55,
        5,
        22,
        39
      ],
      "length": 4,
      "nodes": [
        "22",
        "2",
        "6",
        "19",
        "16"
      ],
      "signature": "chain:22->2->6->19->16",
      "type": "chain"
    },
    {
      "edges": [
        55,
        5,
        18
      ],
      "length": 3,
      "nodes": [
        "22",
        "2",
        "6",
        "8"
      ],
      "signature": "chain:22->2->6->8",
      "type": "chain"
    },
    {
      "edges": [
        55,
        5,
        18,
        23
      ],
      "length": 4,
      "nodes": [
        "22",
        "2",
        "6",
        "8",
        "12"
      ],
      "signature": "chain:22->2->6->8->12",
      "type": "chain"
    },
    {
      "edges": [
        55,
        5,
        18,
        24
      ],
      "length": 4,
      "nodes": [
        "22",
        "2",
        "6",
        "8",
        "17"
      ],
      "signature": "chain:22->2->6->8->17",
      "type": "chain"
    }
  ],
  "feasible_set_hash": "03503b58a9e2383f3e34a69a45f4840bae9a356104949efc34f284875cc57443",
  "max_chain": 4,
  "max_cycle": 3,
  "num_2cycles": 0,
  "num_3cycles": 1,
  "num_arcs": 58,
  "num_chains_total": 119,
  "num_cycles_total": 1,
  "num_feasible_candidates": 120,
  "num_ndds": 2,
  "num_pairs": 20,
  "num_vertices": 22,
  "source_path": "dataset/processed/step3_pairs20_ndd2_step2c_poly_d8_mult_eps050_seed20260619/G-700.json",
  "topology_hash": "a5a8934403fad16fb18b35f0ea0f0b18dcce57b241f0ef05518ed204e5a5f392",
  "topology_id": "G-700",
  "vertices": [
    {
      "id": "0",
      "type": "Pair"
    },
    {
      "id": "1",
      "type": "Pair"
    },
    {
      "id": "2",
      "type": "Pair"
    },
    {
      "id": "3",
      "type": "Pair"
    },
    {
      "id": "4",
      "type": "Pair"
    },
    {
      "id": "5",
      "type": "Pair"
    },
    {
      "id": "6",
      "type": "Pair"
    },
    {
      "id": "7",
      "type": "Pair"
    },
    {
      "id": "8",
      "type": "Pair"
    },
    {
      "id": "9",
      "type": "Pair"
    },
    {
      "id": "10",
      "type": "Pair"
    },
    {
      "id": "11",
      "type": "Pair"
    },
    {
      "id": "12",
      "type": "Pair"
    },
    {
      "id": "13",
      "type": "Pair"
    },
    {
      "id": "14",
      "type": "Pair"
    },
    {
      "id": "16",
      "type": "Pair"
    },
    {
      "id": "17",
      "type": "Pair"
    },
    {
      "id": "18",
      "type": "Pair"
    },
    {
      "id": "19",
      "type": "Pair"
    },
    {
      "id": "20",
      "type": "Pair"
    },
    {
      "id": "21",
      "type": "NDD"
    },
    {
      "id": "22",
      "type": "NDD"
    }
  ]
}
