{
  "arc_order_hash": "2f94ac0a772e26751df2b8b83b89b98db916fc55628dbe5f174990085fa9c2b3",
  "arcs": [
    {
      "edge_idx": 0,
      "source": "2",
      "source_match_position": 0,
      "source_type": "Pair",
      "target": "5",
      "target_type": "Pair"
    },
    {
      "edge_idx": 1,
      "source": "3",
      "source_match_position": 0,
      "source_type": "Pair",
      "target": "0",
      "target_type": "Pair"
    },
    {
      "edge_idx": 2,
      "source": "4",
      "source_match_position": 0,
      "source_type": "Pair",
      "target": "5",
      "target_type": "Pair"
    },
    {
      "edge_idx": 3,
      "source": "4",
      "source_match_position": 1,
      "source_type": "Pair",
      "target": "18",
      "target_type": "Pair"
    },
    {
      "edge_idx": 4,
      "source": "7",
      "source_match_position": 0,
      "source_type": "Pair",
      "target": "1",
      "target_type": "Pair"
    },
    {
      "edge_idx": 5,
      "source": "7",
      "source_match_position": 1,
      "source_type": "Pair",
      "target": "12",
      "target_type": "Pair"
    },
    {
      "edge_idx": 6,
      "source": "7",
      "source_match_position": 2,
      "source_type": "Pair",
      "target": "13",
      "target_type": "Pair"
    },
    {
      "edge_idx": 7,
      "source": "7",
      "source_match_position": 3,
      "source_type": "Pair",
      "target": "14",
      "target_type": "Pair"
    },
    {
      "edge_idx": 8,
      "source": "8",
      "source_match_position": 0,
      "source_type": "Pair",
      "target": "18",
      "target_type": "Pair"
    },
    {
      "edge_idx": 9,
      "source": "9",
      "source_match_position": 0,
      "source_type": "Pair",
      "target": "4",
      "target_type": "Pair"
    },
    {
      "edge_idx": 10,
      "source": "11",
      "source_match_position": 0,
      "source_type": "Pair",
      "target": "14",
      "target_type": "Pair"
    },
    {
      "edge_idx": 11,
      "source": "17",
      "source_match_position": 0,
      "source_type": "Pair",
      "target": "13",
      "target_type": "Pair"
    },
    {
      "edge_idx": 12,
      "source": "17",
      "source_match_position": 1,
      "source_type": "Pair",
      "target": "18",
      "target_type": "Pair"
    },
    {
      "edge_idx": 13,
      "source": "18",
      "source_match_position": 0,
      "source_type": "Pair",
      "target": "5",
      "target_type": "Pair"
    },
    {
      "edge_idx": 14,
      "source": "18",
      "source_match_position": 1,
      "source_type": "Pair",
      "target": "11",
      "target_type": "Pair"
    },
    {
      "edge_idx": 15,
      "source": "19",
      "source_match_position": 0,
      "source_type": "Pair",
      "target": "18",
      "target_type": "Pair"
    },
    {
      "edge_idx": 16,
      "source": "21",
      "source_match_position": 0,
      "source_type": "NDD",
      "target": "14",
      "target_type": "Pair"
    },
    {
      "edge_idx": 17,
      "source": "21",
      "source_match_position": 1,
      "source_type": "NDD",
      "target": "18",
      "target_type": "Pair"
    },
    {
      "edge_idx": 18,
      "source": "22",
      "source_match_position": 0,
      "source_type": "NDD",
      "target": "18",
      "target_type": "Pair"
    }
  ],
  "candidate_conflict_density": 0.9166666666666666,
  "candidate_conflict_edges": 33,
  "feasible_candidates": [
    {
      "edges": [
        16
      ],
      "length": 1,
      "nodes": [
        "21",
        "14"
      ],
      "signature": "chain:21->14",
      "type": "chain"
    },
    {
      "edges": [
        17
      ],
      "length": 1,
      "nodes": [
        "21",
        "18"
      ],
      "signature": "chain:21->18",
      "type": "chain"
    },
    {
      "edges": [
        17,
        14
      ],
      "length": 2,
      "nodes": [
        "21",
        "18",
        "11"
      ],
      "signature": "chain:21->18->11",
      "type": "chain"
    },
    {
      "edges": [
        17,
        14,
        10
      ],
      "length": 3,
      "nodes": [
        "21",
        "18",
        "11",
        "14"
      ],
      "signature": "chain:21->18->11->14",
      "type": "chain"
    },
    {
      "edges": [
        17,
        13
      ],
      "length": 2,
      "nodes": [
        "21",
        "18",
        "5"
      ],
      "signature": "chain:21->18->5",
      "type": "chain"
    },
    {
      "edges": [
        18
      ],
      "length": 1,
      "nodes": [
        "22",
        "18"
      ],
      "signature": "chain:22->18",
      "type": "chain"
    },
    {
      "edges": [
        18,
        14
      ],
      "length": 2,
      "nodes": [
        "22",
        "18",
        "11"
      ],
      "signature": "chain:22->18->11",
      "type": "chain"
    },
    {
      "edges": [
        18,
        14,
        10
      ],
      "length": 3,
      "nodes": [
        "22",
        "18",
        "11",
        "14"
      ],
      "signature": "chain:22->18->11->14",
      "type": "chain"
    },
    {
      "edges": [
        18,
        13
      ],
      "length": 2,
      "nodes": [
        "22",
        "18",
        "5"
      ],
      "signature": "chain:22->18->5",
      "type": "chain"
    }
  ],
  "feasible_set_hash": "fcafcedcacc6599e68eeee738c5d5f2df72d998ec6fde0110337d7a957d706e9",
  "fraction_vertices_in_any_candidate": 0.2727272727272727,
  "largest_conflict_component_fraction": 1.0,
  "max_candidates_per_vertex": 8,
  "max_chain": 4,
  "max_conflict_degree": 8,
  "max_cycle": 3,
  "mean_candidates_per_vertex": 1.1818181818181819,
  "mean_conflict_degree": 7.333333333333333,
  "num_2cycles": 0,
  "num_3cycles": 0,
  "num_arcs": 19,
  "num_chains_len1": 3,
  "num_chains_len2": 4,
  "num_chains_len3": 2,
  "num_chains_len4": 0,
  "num_chains_total": 9,
  "num_conflict_components": 1,
  "num_cycles_total": 0,
  "num_exchange_candidates": 9,
  "num_feasible_candidates": 9,
  "num_ndds": 2,
  "num_pairs": 20,
  "num_vertices": 22,
  "num_vertices_in_any_candidate": 6,
  "source_path": "dataset/processed/step3_pairs20_ndd2_step2c_poly_d8_mult_eps050_seed20260619/G-655.json",
  "topology_hash": "0e2a3455893b99ac343213468f6252716f64a6083d462ddf2569b6d40e47f50d",
  "topology_id": "G-655",
  "vertices": [
    {
      "id": "0",
      "type": "Pair"
    },
    {
      "id": "1",
      "type": "Pair"
    },
    {
      "id": "2",
      "type": "Pair"
    },
    {
      "id": "3",
      "type": "Pair"
    },
    {
      "id": "4",
      "type": "Pair"
    },
    {
      "id": "5",
      "type": "Pair"
    },
    {
      "id": "6",
      "type": "Pair"
    },
    {
      "id": "7",
      "type": "Pair"
    },
    {
      "id": "8",
      "type": "Pair"
    },
    {
      "id": "9",
      "type": "Pair"
    },
    {
      "id": "11",
      "type": "Pair"
    },
    {
      "id": "12",
      "type": "Pair"
    },
    {
      "id": "13",
      "type": "Pair"
    },
    {
      "id": "14",
      "type": "Pair"
    },
    {
      "id": "15",
      "type": "Pair"
    },
    {
      "id": "16",
      "type": "Pair"
    },
    {
      "id": "17",
      "type": "Pair"
    },
    {
      "id": "18",
      "type": "Pair"
    },
    {
      "id": "19",
      "type": "Pair"
    },
    {
      "id": "20",
      "type": "Pair"
    },
    {
      "id": "21",
      "type": "NDD"
    },
    {
      "id": "22",
      "type": "NDD"
    }
  ]
}
