{
  "arc_order_hash": "7b574df814e69b264709d77843ef5e615a58a86a4cd895330eec2ffcd8075d08",
  "arcs": [
    {
      "edge_idx": 0,
      "source": "0",
      "source_match_position": 0,
      "source_type": "Pair",
      "target": "4",
      "target_type": "Pair"
    },
    {
      "edge_idx": 1,
      "source": "1",
      "source_match_position": 0,
      "source_type": "Pair",
      "target": "2",
      "target_type": "Pair"
    },
    {
      "edge_idx": 2,
      "source": "1",
      "source_match_position": 1,
      "source_type": "Pair",
      "target": "14",
      "target_type": "Pair"
    },
    {
      "edge_idx": 3,
      "source": "1",
      "source_match_position": 2,
      "source_type": "Pair",
      "target": "17",
      "target_type": "Pair"
    },
    {
      "edge_idx": 4,
      "source": "3",
      "source_match_position": 0,
      "source_type": "Pair",
      "target": "21",
      "target_type": "Pair"
    },
    {
      "edge_idx": 5,
      "source": "4",
      "source_match_position": 0,
      "source_type": "Pair",
      "target": "12",
      "target_type": "Pair"
    },
    {
      "edge_idx": 6,
      "source": "4",
      "source_match_position": 1,
      "source_type": "Pair",
      "target": "17",
      "target_type": "Pair"
    },
    {
      "edge_idx": 7,
      "source": "4",
      "source_match_position": 2,
      "source_type": "Pair",
      "target": "21",
      "target_type": "Pair"
    },
    {
      "edge_idx": 8,
      "source": "5",
      "source_match_position": 0,
      "source_type": "Pair",
      "target": "4",
      "target_type": "Pair"
    },
    {
      "edge_idx": 9,
      "source": "8",
      "source_match_position": 0,
      "source_type": "Pair",
      "target": "14",
      "target_type": "Pair"
    },
    {
      "edge_idx": 10,
      "source": "10",
      "source_match_position": 0,
      "source_type": "Pair",
      "target": "14",
      "target_type": "Pair"
    },
    {
      "edge_idx": 11,
      "source": "11",
      "source_match_position": 0,
      "source_type": "Pair",
      "target": "2",
      "target_type": "Pair"
    },
    {
      "edge_idx": 12,
      "source": "11",
      "source_match_position": 1,
      "source_type": "Pair",
      "target": "10",
      "target_type": "Pair"
    },
    {
      "edge_idx": 13,
      "source": "12",
      "source_match_position": 0,
      "source_type": "Pair",
      "target": "4",
      "target_type": "Pair"
    },
    {
      "edge_idx": 14,
      "source": "15",
      "source_match_position": 0,
      "source_type": "Pair",
      "target": "12",
      "target_type": "Pair"
    },
    {
      "edge_idx": 15,
      "source": "15",
      "source_match_position": 1,
      "source_type": "Pair",
      "target": "21",
      "target_type": "Pair"
    },
    {
      "edge_idx": 16,
      "source": "16",
      "source_match_position": 0,
      "source_type": "Pair",
      "target": "1",
      "target_type": "Pair"
    },
    {
      "edge_idx": 17,
      "source": "16",
      "source_match_position": 1,
      "source_type": "Pair",
      "target": "2",
      "target_type": "Pair"
    },
    {
      "edge_idx": 18,
      "source": "16",
      "source_match_position": 2,
      "source_type": "Pair",
      "target": "17",
      "target_type": "Pair"
    },
    {
      "edge_idx": 19,
      "source": "18",
      "source_match_position": 0,
      "source_type": "Pair",
      "target": "11",
      "target_type": "Pair"
    },
    {
      "edge_idx": 20,
      "source": "18",
      "source_match_position": 1,
      "source_type": "Pair",
      "target": "17",
      "target_type": "Pair"
    },
    {
      "edge_idx": 21,
      "source": "18",
      "source_match_position": 2,
      "source_type": "Pair",
      "target": "20",
      "target_type": "Pair"
    },
    {
      "edge_idx": 22,
      "source": "18",
      "source_match_position": 3,
      "source_type": "Pair",
      "target": "21",
      "target_type": "Pair"
    },
    {
      "edge_idx": 23,
      "source": "19",
      "source_match_position": 0,
      "source_type": "Pair",
      "target": "21",
      "target_type": "Pair"
    },
    {
      "edge_idx": 24,
      "source": "20",
      "source_match_position": 0,
      "source_type": "Pair",
      "target": "4",
      "target_type": "Pair"
    },
    {
      "edge_idx": 25,
      "source": "20",
      "source_match_position": 1,
      "source_type": "Pair",
      "target": "14",
      "target_type": "Pair"
    },
    {
      "edge_idx": 26,
      "source": "21",
      "source_match_position": 0,
      "source_type": "Pair",
      "target": "1",
      "target_type": "Pair"
    },
    {
      "edge_idx": 27,
      "source": "21",
      "source_match_position": 1,
      "source_type": "Pair",
      "target": "12",
      "target_type": "Pair"
    },
    {
      "edge_idx": 28,
      "source": "22",
      "source_match_position": 0,
      "source_type": "NDD",
      "target": "11",
      "target_type": "Pair"
    },
    {
      "edge_idx": 29,
      "source": "23",
      "source_match_position": 0,
      "source_type": "NDD",
      "target": "4",
      "target_type": "Pair"
    }
  ],
  "feasible_candidates": [
    {
      "edges": [
        5,
        13
      ],
      "length": 2,
      "nodes": [
        "4",
        "12"
      ],
      "signature": "cycle:4->12->4",
      "type": "cycle"
    },
    {
      "edges": [
        7,
        27,
        13
      ],
      "length": 3,
      "nodes": [
        "4",
        "21",
        "12"
      ],
      "signature": "cycle:4->21->12->4",
      "type": "cycle"
    },
    {
      "edges": [
        28
      ],
      "length": 1,
      "nodes": [
        "22",
        "11"
      ],
      "signature": "chain:22->11",
      "type": "chain"
    },
    {
      "edges": [
        28,
        12
      ],
      "length": 2,
      "nodes": [
        "22",
        "11",
        "10"
      ],
      "signature": "chain:22->11->10",
      "type": "chain"
    },
    {
      "edges": [
        28,
        12,
        10
      ],
      "length": 3,
      "nodes": [
        "22",
        "11",
        "10",
        "14"
      ],
      "signature": "chain:22->11->10->14",
      "type": "chain"
    },
    {
      "edges": [
        28,
        11
      ],
      "length": 2,
      "nodes": [
        "22",
        "11",
        "2"
      ],
      "signature": "chain:22->11->2",
      "type": "chain"
    },
    {
      "edges": [
        29
      ],
      "length": 1,
      "nodes": [
        "23",
        "4"
      ],
      "signature": "chain:23->4",
      "type": "chain"
    },
    {
      "edges": [
        29,
        5
      ],
      "length": 2,
      "nodes": [
        "23",
        "4",
        "12"
      ],
      "signature": "chain:23->4->12",
      "type": "chain"
    },
    {
      "edges": [
        29,
        6
      ],
      "length": 2,
      "nodes": [
        "23",
        "4",
        "17"
      ],
      "signature": "chain:23->4->17",
      "type": "chain"
    },
    {
      "edges": [
        29,
        7
      ],
      "length": 2,
      "nodes": [
        "23",
        "4",
        "21"
      ],
      "signature": "chain:23->4->21",
      "type": "chain"
    },
    {
      "edges": [
        29,
        7,
        26
      ],
      "length": 3,
      "nodes": [
        "23",
        "4",
        "21",
        "1"
      ],
      "signature": "chain:23->4->21->1",
      "type": "chain"
    },
    {
      "edges": [
        29,
        7,
        26,
        2
      ],
      "length": 4,
      "nodes": [
        "23",
        "4",
        "21",
        "1",
        "14"
      ],
      "signature": "chain:23->4->21->1->14",
      "type": "chain"
    },
    {
      "edges": [
        29,
        7,
        26,
        3
      ],
      "length": 4,
      "nodes": [
        "23",
        "4",
        "21",
        "1",
        "17"
      ],
      "signature": "chain:23->4->21->1->17",
      "type": "chain"
    },
    {
      "edges": [
        29,
        7,
        26,
        1
      ],
      "length": 4,
      "nodes": [
        "23",
        "4",
        "21",
        "1",
        "2"
      ],
      "signature": "chain:23->4->21->1->2",
      "type": "chain"
    },
    {
      "edges": [
        29,
        7,
        27
      ],
      "length": 3,
      "nodes": [
        "23",
        "4",
        "21",
        "12"
      ],
      "signature": "chain:23->4->21->12",
      "type": "chain"
    }
  ],
  "feasible_set_hash": "3c08cf7ebf72021d4b0e4b29ee4fbccb3f05f21301d2bca3e80c1c95c73c1a8f",
  "max_chain": 4,
  "max_cycle": 3,
  "num_2cycles": 1,
  "num_3cycles": 1,
  "num_arcs": 30,
  "num_chains_total": 13,
  "num_cycles_total": 2,
  "num_feasible_candidates": 15,
  "num_ndds": 2,
  "num_pairs": 20,
  "num_vertices": 22,
  "source_path": "dataset/processed/step3_pairs20_ndd2_step2c_poly_d8_mult_eps050_seed20260619/G-300.json",
  "topology_hash": "1e3eaf739394cc78b2120438820f70f157d3af1beac759d098cae3ecb0e9b5c2",
  "topology_id": "G-300",
  "vertices": [
    {
      "id": "0",
      "type": "Pair"
    },
    {
      "id": "1",
      "type": "Pair"
    },
    {
      "id": "2",
      "type": "Pair"
    },
    {
      "id": "3",
      "type": "Pair"
    },
    {
      "id": "4",
      "type": "Pair"
    },
    {
      "id": "5",
      "type": "Pair"
    },
    {
      "id": "6",
      "type": "Pair"
    },
    {
      "id": "8",
      "type": "Pair"
    },
    {
      "id": "10",
      "type": "Pair"
    },
    {
      "id": "11",
      "type": "Pair"
    },
    {
      "id": "12",
      "type": "Pair"
    },
    {
      "id": "13",
      "type": "Pair"
    },
    {
      "id": "14",
      "type": "Pair"
    },
    {
      "id": "15",
      "type": "Pair"
    },
    {
      "id": "16",
      "type": "Pair"
    },
    {
      "id": "17",
      "type": "Pair"
    },
    {
      "id": "18",
      "type": "Pair"
    },
    {
      "id": "19",
      "type": "Pair"
    },
    {
      "id": "20",
      "type": "Pair"
    },
    {
      "id": "21",
      "type": "Pair"
    },
    {
      "id": "22",
      "type": "NDD"
    },
    {
      "id": "23",
      "type": "NDD"
    }
  ]
}
