{
  "arc_order_hash": "83e7927db1f799b6e9002ccbf47ad20b706f0d363547676785609aece3f73ea1",
  "arcs": [
    {
      "edge_idx": 0,
      "source": "1",
      "source_match_position": 0,
      "source_type": "Pair",
      "target": "3",
      "target_type": "Pair"
    },
    {
      "edge_idx": 1,
      "source": "1",
      "source_match_position": 1,
      "source_type": "Pair",
      "target": "5",
      "target_type": "Pair"
    },
    {
      "edge_idx": 2,
      "source": "6",
      "source_match_position": 0,
      "source_type": "Pair",
      "target": "4",
      "target_type": "Pair"
    },
    {
      "edge_idx": 3,
      "source": "8",
      "source_match_position": 0,
      "source_type": "NDD",
      "target": "7",
      "target_type": "Pair"
    },
    {
      "edge_idx": 4,
      "source": "9",
      "source_match_position": 0,
      "source_type": "NDD",
      "target": "5",
      "target_type": "Pair"
    }
  ],
  "feasible_candidates": [
    {
      "edges": [
        3
      ],
      "length": 1,
      "nodes": [
        "8",
        "7"
      ],
      "signature": "chain:8->7",
      "type": "chain"
    },
    {
      "edges": [
        4
      ],
      "length": 1,
      "nodes": [
        "9",
        "5"
      ],
      "signature": "chain:9->5",
      "type": "chain"
    }
  ],
  "feasible_set_hash": "52392bfc4be3e5850539cf1987e78c46ca3580db21314651230bc9bfb3c2da3a",
  "max_chain": 4,
  "max_cycle": 3,
  "num_2cycles": 0,
  "num_3cycles": 0,
  "num_arcs": 5,
  "num_chains_total": 2,
  "num_cycles_total": 0,
  "num_feasible_candidates": 2,
  "num_ndds": 2,
  "num_pairs": 7,
  "num_vertices": 9,
  "source_path": "dataset/processed/step3_pairs7_step2c_poly_d8_mult_eps050_seed20260619/G-13.json",
  "topology_hash": "2f666bb5e6b712ecc4f4a6e00510fba6f92392c3a70d23b772cfcca8945cca46",
  "topology_id": "G-13",
  "vertices": [
    {
      "id": "1",
      "type": "Pair"
    },
    {
      "id": "2",
      "type": "Pair"
    },
    {
      "id": "3",
      "type": "Pair"
    },
    {
      "id": "4",
      "type": "Pair"
    },
    {
      "id": "5",
      "type": "Pair"
    },
    {
      "id": "6",
      "type": "Pair"
    },
    {
      "id": "7",
      "type": "Pair"
    },
    {
      "id": "8",
      "type": "NDD"
    },
    {
      "id": "9",
      "type": "NDD"
    }
  ]
}
